esMPRA/__init__.py
esMPRA/generate_data_for_MPRAnalyse.py
esMPRA/qc_step1.py
esMPRA/qc_step2.py
esMPRA/qc_step3.py
esMPRA/qc_step4.py
esMPRA/step1_oligo_barcode_map.py
esMPRA/step2_get_plasmid_counts.py
esMPRA/step3_get_RNA_counts.py
esMPRA/step4_get_result.py
esMPRA/step5_compare_diff_rep.py
esMPRA/data/step1_refdata.pkl
esMPRA/data/step2_refdata.pkl
esMPRA/data/step3_refdata.pkl
esMPRA/data/step4_refdata.pkl
esMPRA-1.0.0.dist-info/METADATA
esMPRA-1.0.0.dist-info/WHEEL
esMPRA-1.0.0.dist-info/entry_points.txt
esMPRA-1.0.0.dist-info/top_level.txt
esMPRA-1.0.0.dist-info/RECORD
