Metadata-Version: 2.1
Name: esMPRA
Version: 1.0.0
Summary: An easy to use pipeline for MPRA experiment quality control and data processing
Home-page: https://github.com/KachesL/esMPRA
Author: Jiaqi Li
Author-email: kaches@foxmail.com
License: UNKNOWN
Platform: UNKNOWN
Classifier: Programming Language :: Python :: 3
Classifier: License :: OSI Approved :: MIT License
Classifier: Operating System :: OS Independent
Requires-Python: >=3.6
Requires-Dist: numpy (>=1.18.0)
Requires-Dist: matplotlib
Requires-Dist: pandas
Requires-Dist: reportlab
